{
  "node_id": "seguridad_trabajadores_jovenes",
  "fase_proyecto": "planificacion",
  "dominio": "health_safety",
  "titulo_concepto": "Seguridad de Trabajadores Jóvenes",
  "fuente": "SMALL_BUSINESS",
  "resumen_teorico": "Los trabajadores jóvenes tienen aproximadamente el doble de riesgo de lesión que los adultos debido a su falta de experiencia y reticencia a hacer preguntas. Se deben cumplir leyes laborales infantiles (edad mínima, horas de trabajo, tareas prohibidas), proporcionar capacitación específica sobre riesgos, y fomentar un ambiente donde puedan reportar condiciones inseguras sin temor a represalias.",
  "pasos_accionables": [
    "Verificar cumplimiento de leyes estatales y federales de trabajo infantil por edad",
    "Confirmar que trabajadores menores de 18 no operen equipo peligroso prohibido",
    "Obtener permisos de trabajo requeridos por ley estatal",
    "Capacitar a gerentes y compañeros sobre leyes de trabajo infantil",
    "Proveer capacitación específica sobre riesgos y prácticas seguras a jóvenes",
    "Reforzar información de seguridad durante las primeras semanas de trabajo",
    "Comunicar que no habrá represalias por reportar condiciones inseguras o lesiones",
    "Fomentar participación en entrenamientos OSHA de 10 horas cuando sea posible"
  ],
  "entregable_esperado": "Checklist de cumplimiento de leyes de trabajo infantil y plan de capacitación específico para trabajadores jóvenes.",
  "nodos_previos": [
    "capacitacion_seguridad_trabajadores"
  ],
  "nodos_siguientes": [],
  "condiciones_activacion": [
    "Si la empresa emplea trabajadores menores de 18 años"
  ]
}