{
  "node_id": "batna_en_negociacion_vc",
  "fase_proyecto": "planificacion",
  "titulo_concepto": "BATNA: Mejor Alternativa a un Acuerdo Negociado",
  "fuente": "Venture Deals",
  "resumen_teorico": "El BATNA (Best Alternative To a Negotiated Agreement) es el concepto de tener un 'Plan B' sólido detrás del 'Plan A' en cualquier negociación de financiamiento. Cuantos más inversionistas potenciales interesados tenga el emprendedor, mejor será su posición negociadora frente a cualquier VC individual.",
  "pasos_accionables": [
    "Desarrollar y mantener conversaciones activas con múltiples inversionistas potenciales antes y durante la negociación principal.",
    "Invertir tiempo significativo en fortalecer las alternativas disponibles, no solo en la negociación principal.",
    "Usar la existencia de alternativas reales (sin exagerar) como palanca de negociación."
  ],
  "entregable_esperado": "Un pipeline activo de al menos 2-3 inversionistas potenciales en conversación simultánea antes de cerrar una ronda.",
  "nodos_previos": [
    "estrategia_fundraising"
  ],
  "nodos_siguientes": [
    "negociacion_valoracion",
    "cierre_de_ronda"
  ],
  "condiciones_activacion": [
    "Cuando el usuario está a punto de entrar en negociación con un solo inversionista",
    "Cuando se busca maximizar el poder de negociación en una ronda"
  ]
}