{
  "node_id": "diferencia_planeacion_mejora",
  "fase_proyecto": "ideacion",
  "dominio": "quality",
  "titulo_concepto": "Diferencia entre Planeación de Calidad y Mejora de Calidad",
  "fuente": "Juran's Quality Handbook_ The C - Joseph A. Defeo",
  "resumen_teorico": "Distinción conceptual clave: la planeación de calidad se enfoca en diseñar nuevas características de producto o servicio para satisfacer al cliente y generar ingresos (breakthrough en diseño), mientras que la mejora de calidad se enfoca en reducir fallas y desperdicio no generador de valor en procesos ya existentes (breakthrough en desempeño). Ambos tipos de breakthrough requieren metodologías distintas.",
  "pasos_accionables": [
    "Determinar si el objetivo es crear nuevas características (planeación) o reducir fallas existentes (mejora)",
    "Si es planeación: iniciar con la 'voz del cliente' y diseño de producto",
    "Si es mejora: iniciar con diagnóstico de causas de fallas en procesos actuales",
    "Asignar la metodología correspondiente (quality by design vs breakthrough improvement)"
  ],
  "entregable_esperado": "Clasificación clara del tipo de proyecto (diseño vs mejora) antes de iniciar la metodología",
  "nodos_previos": [],
  "nodos_siguientes": [
    "secuencia_universal_breakthrough",
    "planeacion_de_calidad_juran"
  ],
  "condiciones_activacion": [
    "Al inicio de cualquier iniciativa de calidad, para decidir qué metodología aplicar"
  ]
}