{
  "node_id": "ejecucion_auditoria",
  "fase_proyecto": "ejecucion",
  "dominio": "quality",
  "titulo_concepto": "Ejecución y Verificación de Hechos en la Auditoría",
  "fuente": "Juran's Quality Handbook_ The C - Joseph A. Defeo",
  "resumen_teorico": "Durante la ejecución, los auditores deben verificar los hechos (síntomas observables) con la supervisión de línea antes de incluirlos en el reporte. Se debe decidir si el auditor investigará las causas de las deficiencias mayores o si esto queda a cargo del personal de línea. Los auditores generalmente deben hacer recomendaciones pero evitar diseñar los remedios ellos mismos.",
  "pasos_accionables": [
    "Verificar y acordar los hechos encontrados con la supervisión de línea antes de reportarlos",
    "Determinar el alcance de la investigación de causas (auditor vs. personal de línea)",
    "Formular recomendaciones de mejora sin diseñar directamente las soluciones",
    "Mantener informado al cliente clave sobre el avance de la auditoría (status reporting)"
  ],
  "entregable_esperado": "Registro de hallazgos verificados y acordados con el área auditada",
  "nodos_previos": [
    "checklist_estandares_auditoria"
  ],
  "nodos_siguientes": [
    "reporte_auditoria",
    "relaciones_humanas_auditoria"
  ],
  "condiciones_activacion": [
    "Cuando se está en la fase activa de recolección de evidencia de la auditoría"
  ]
}