{
  "node_id": "fitness_for_use_purpose",
  "fase_proyecto": "ideacion",
  "dominio": "quality",
  "titulo_concepto": "Fitness for Use / Fitness for Purpose",
  "fuente": "Juran's Quality Handbook_ The C - Joseph A. Defeo",
  "resumen_teorico": "Definición central de calidad según Juran: 'calidad' significa aptitud para el uso, extendida a 'aptitud para el propósito'. Incorpora dos dimensiones: presencia de características que generan satisfacción y ausencia de fallas. Es el usuario quien decide qué significa 'uso' y 'aptitud', no el proveedor. Distingue entre uso previsto (intended use) y uso real (actual use), y entre uso creativo del cliente y abuso del producto.",
  "pasos_accionables": [
    "Identificar el uso previsto original del producto o servicio",
    "Investigar los usos reales que los clientes le dan (incluyendo usos no previstos)",
    "Diferenciar entre uso creativo legítimo y abuso fuera del alcance de diseño",
    "Diseñar considerando la tolerancia a usos no previstos razonables"
  ],
  "entregable_esperado": "Documento de definición de 'aptitud para el uso/propósito' aplicado al producto o servicio en diseño",
  "nodos_previos": [],
  "nodos_siguientes": [
    "descubrir_necesidades_cliente",
    "desarrollar_caracteristicas_producto"
  ],
  "condiciones_activacion": [
    "Cuando se define qué es calidad para un producto específico",
    "Cuando existe confusión entre satisfacción del cliente y ausencia de quejas"
  ]
}