{
  "node_id": "politica_calidad_organizacional",
  "fase_proyecto": "planificacion",
  "dominio": "quality",
  "titulo_concepto": "Política de Calidad Organizacional",
  "fuente": "Juran's Quality Handbook_ The C - Joseph A. Defeo",
  "resumen_teorico": "La política de calidad es una declaración formal que guía las decisiones y acciones gerenciales, estableciendo el valor relativo que la organización otorga a la calidad frente a la cantidad de producción. Debe reflejarse en el manual organizacional y reforzar normas culturales instrumentales necesarias para lograr una 'cultura de calidad'. Si no se hace cumplir, pierde su valor y puede percibirse como un engaño.",
  "pasos_accionables": [
    "Redactar una declaración de política de calidad que priorice la satisfacción del cliente y la reducción de costos de mala calidad",
    "Incluir la política en el manual organizacional",
    "Comunicar la política a toda la organización",
    "Establecer mecanismos de seguimiento y cumplimiento de la política"
  ],
  "entregable_esperado": "Declaración de política de calidad documentada e integrada en el manual organizacional, con mecanismo de cumplimiento",
  "nodos_previos": [
    "codigo_conducta_orientado_cliente"
  ],
  "nodos_siguientes": [
    "cultura_calidad",
    "recursos_humanos_cultura"
  ],
  "condiciones_activacion": [
    "Cuando se inicia un manual de calidad organizacional",
    "Si la organización necesita alinear decisiones gerenciales con objetivos de calidad"
  ]
}