{
  "node_id": "warrants_financiamiento",
  "fase_proyecto": "planificacion",
  "titulo_concepto": "Warrants en Financiamientos de Etapas Posteriores",
  "fuente": "Venture Deals - Brad Feld",
  "resumen_teorico": "Un warrant es el derecho a comprar un número determinado de acciones a un precio predefinido durante un periodo de años, similar a una opción. Son otra forma en que un inversor puede reducir efectivamente la valuación de la empresa, y suelen generar complejidad contable innecesaria, especialmente en rondas tempranas.",
  "pasos_accionables": [
    "Identificar si el term sheet incluye warrants y su impacto en la valuación efectiva.",
    "Negociar una valuación pre-money más baja como alternativa a aceptar warrants.",
    "Evaluar la complejidad contable adicional que introducen los warrants antes de aceptarlos."
  ],
  "entregable_esperado": "Decisión documentada sobre aceptar o negociar la eliminación de warrants en el term sheet.",
  "nodos_previos": [
    "pool_opciones_empleados"
  ],
  "nodos_siguientes": [],
  "condiciones_activacion": [
    "Cuando el term sheet de una ronda de etapa avanzada incluye cláusulas de warrants."
  ]
}