{
  "node_id": "aim_of_leadership",
  "fase_proyecto": "ejecucion",
  "dominio": "quality",
  "titulo_concepto": "Objetivo del Liderazgo (Deming)",
  "fuente": "Out of the Crisis, Reissue - Deming, W. Edwards; Cahill, Kev",
  "resumen_teorico": "El propósito del liderazgo no es encontrar y registrar fallas de las personas, sino eliminar las causas de las fallas para ayudar a la gente a trabajar mejor con menos esfuerzo. El líder tiene tres responsabilidades: identificar quién está fuera del sistema (necesitando ayuda o reconocimiento), mejorar el sistema continuamente, y lograr mayor consistencia de desempeño reduciendo las diferencias aparentes entre personas.",
  "pasos_accionables": [
    "Identificar mediante datos o juicio quién está fuera del sistema, ya sea por bajo o alto desempeño",
    "Investigar las causas raíz del sistema que afectan el desempeño general",
    "Trabajar continuamente en mejorar el sistema para todos, no solo corregir individuos",
    "Reconocer y estudiar a quienes tienen desempeño excepcional para replicar sus métodos"
  ],
  "entregable_esperado": "Un plan de liderazgo enfocado en mejora del sistema con identificación de casos individuales fuera de control",
  "nodos_previos": [
    "control_estadistico_de_procesos"
  ],
  "nodos_siguientes": [
    "distincion_causas_comunes_especiales",
    "administracion_sin_miedo"
  ],
  "condiciones_activacion": [
    "Cuando un líder busca mejorar el desempeño de su equipo",
    "Cuando se detectan fallas recurrentes atribuidas erróneamente a los trabajadores"
  ]
}