{
  "node_id": "customer_types_mapping",
  "fase_proyecto": "validacion",
  "titulo_concepto": "Mapeo de Tipos de Cliente en la Decisión de Compra",
  "fuente": "The Startup Owner's Manual - Steve Blank",
  "resumen_teorico": "Toda venta involucra múltiples roles de decisión que rara vez son la misma persona: usuarios finales (usan el producto), influenciadores (opinan pero no deciden), recomendadores (su opinión puede hacer o deshacer la venta), compradores económicos (controlan el presupuesto), decisores (autoridad final de compra) y saboteadores (pueden vetar la compra). Identificar y entender a cada uno es esencial, especialmente en ventas B2B complejas.",
  "pasos_accionables": [
    "Listar quién usará el producto día a día (usuario final)",
    "Identificar influenciadores y recomendadores externos e internos",
    "Determinar quién controla el presupuesto (comprador económico)",
    "Identificar al decisor final (UDM/VITO)",
    "Detectar posibles saboteadores que puedan vetar la compra"
  ],
  "entregable_esperado": "Mapa de roles de decisión de compra con nombres/perfiles para cada tipo de cliente",
  "nodos_previos": [
    "customer_segments_hypothesis"
  ],
  "nodos_siguientes": [
    "mapa_organizacional_influencia",
    "consecuencias_no_intencionadas_sistemicas",
    "flexible_go_kill_criteria",
    "manejo_de_incertidumbre_proyectos_innovadores",
    "pensar_en_grande_empezar_pequeno",
    "customer_archetypes"
  ],
  "condiciones_activacion": [
    "Si el producto se vende en un contexto B2B complejo",
    "Cuando la venta involucra más de una persona en la decisión"
  ]
}