{
  "node_id": "desarrollo_en_espiral",
  "fase_proyecto": "ejecucion",
  "titulo_concepto": "Desarrollo en Espiral o Iterativo (Build-Test-Feedback-Revise)",
  "fuente": "Winning at New Products - Robert G. Cooper",
  "resumen_teorico": "Práctica que permite que el producto no esté completamente definido al iniciar el desarrollo (menos del 50%), sino que evolucione mediante múltiples ciclos de construir un prototipo, probarlo con clientes, recoger feedback y revisar el diseño. Cada espiral acerca el proyecto al diseño final, fomentando la experimentación y el fallo rápido, barato y temprano.",
  "pasos_accionables": [
    "Construir una versión mínima demostrable (prototipo, MVP, protocept) del producto",
    "Probar la versión con clientes reales para medir interés, preferencia e intención de compra",
    "Recoger feedback directo sobre qué debe cambiarse o corregirse",
    "Revisar el diseño, propuesta de valor y beneficios en base al feedback",
    "Repetir el ciclo hasta convergir en el diseño final del producto"
  ],
  "entregable_esperado": "Una serie de prototipos iterativos con registros de feedback de cliente en cada ciclo, culminando en una definición de producto validada",
  "nodos_previos": [
    "sistema_triple_a_stage_gate",
    "backlog_evolutivo_y_cronograma_flexible",
    "co_creation_session",
    "rapid_prototyping",
    "role_playing",
    "roles_product_owner_scrum_master",
    "storyboard",
    "voc_temprano_en_agile_stage_gate"
  ],
  "nodos_siguientes": [
    "modelo_contingencia_riesgo"
  ],
  "condiciones_activacion": [
    "Si los clientes no tienen claro lo que quieren o necesitan",
    "Si el proyecto es de alto riesgo o innovación radical",
    "Si los requerimientos del producto pueden cambiar durante el desarrollo"
  ]
}