{
  "node_id": "design_thinking_fundamentos",
  "fase_proyecto": "ideacion",
  "dominio": "core",
  "titulo_concepto": "Design Thinking: Un Enfoque Centrado en el Humano para la Innovación",
  "fuente": "Change by Design - Tim Brown",
  "resumen_teorico": "Design Thinking es un enfoque de innovación que integra lo deseable desde el punto de vista humano con lo tecnológicamente factible y lo económicamente viable. A diferencia del diseño tradicional (enfocado en estilo o estética), el design thinking pone a las personas en el centro del proceso creativo, utilizando la intuición, el reconocimiento de patrones y la construcción de significado emocional junto con el razonamiento analítico. No es exclusivo de diseñadores profesionales; es una capacidad humana que puede aplicarse a negocios, organizaciones sociales y problemas complejos ('wicked problems').",
  "pasos_accionables": [
    "Identificar un problema u oportunidad que vaya más allá de mejorar un producto existente",
    "Reunir un equipo interdisciplinario (diseñadores, científicos del comportamiento, ingenieros, marketing)",
    "Enfocar la exploración inicial en las necesidades humanas antes que en las especificaciones técnicas",
    "Balancear deseabilidad humana, viabilidad técnica y factibilidad económica en cada decisión"
  ],
  "entregable_esperado": "Un marco de trabajo interdisciplinario documentado que defina el problema desde la perspectiva humana, técnica y económica antes de iniciar el desarrollo de soluciones.",
  "nodos_previos": [
    "reconocer_sesgo_de_apofenia"
  ],
  "nodos_siguientes": [
    "convertir_necesidad_en_demanda",
    "mapeo_capas_diseno",
    "diseno_activismo_social",
    "diseno_estrategico_vs_tactico",
    "diseno_intencional_etica",
    "how_might_we_framing",
    "mastery_sensibilidades_diseno"
  ],
  "condiciones_activacion": [
    "Cuando el usuario enfrenta un problema complejo que la innovación tecnológica o incremental no ha resuelto",
    "Cuando se busca ir más allá del diseño estético hacia la estrategia de negocio"
  ],
  "etiqueta_arbol": "Piensa Centrado en las Personas"
}
