{
  "node_id": "determinar_monto_a_levantar",
  "fase_proyecto": "planificacion",
  "dominio": "core",
  "titulo_concepto": "Determinar el Monto a Levantar en una Ronda",
  "fuente": "Venture Deals",
  "resumen_teorico": "En vez de crear modelos financieros complejos que inevitablemente serán incorrectos, el emprendedor debe enfocarse en el tiempo que necesita para llegar al siguiente hito significativo, calcular el burn rate mensual necesario, y añadir un colchón de tiempo. Es crucial pedir una cifra específica (no un rango) y evitar pedir montos significativamente mayores a lo necesario para no quedar mal posicionado si no se completa la ronda.",
  "pasos_accionables": [
    "Definir el próximo hito significativo del negocio (ej. lanzar producto, alcanzar X usuarios)",
    "Calcular el burn rate mensual necesario para llegar a ese hito",
    "Añadir un colchón de tiempo (ej. hasta un año)",
    "Definir una cifra específica de levantamiento, no un rango",
    "Evitar pedir montos muy superiores a la necesidad real"
  ],
  "entregable_esperado": "Monto específico de financiamiento definido con justificación de burn rate y milestone",
  "nodos_previos": [
    "proteccion_propiedad_intelectual"
  ],
  "nodos_siguientes": [
    "preparacion_materiales_fundraising"
  ],
  "condiciones_activacion": [
    "Antes de iniciar el proceso formal de fundraising",
    "Si el usuario no tiene claridad sobre cuánto capital necesita"
  ],
  "etiqueta_arbol": "Calcula Cuánto Capital Levantar"
}
