{
  "node_id": "hipotesis_de_tamano_de_mercado",
  "fase_proyecto": "ideacion",
  "titulo_concepto": "Hipótesis de Tamaño de Mercado (TAM, SAM, Target Market)",
  "fuente": "The Startup Owner's Manual - Steve Blank",
  "resumen_teorico": "Antes de invertir años en una startup, es crucial estimar el tamaño de la oportunidad usando tres métricas: TAM (mercado total direccionable), SAM (mercado disponible que se puede atender con el canal de ventas) y Target Market (compradores más probables). Se recomienda una estimación 'bottom-up' más realista que las estimaciones 'top-down' de firmas de investigación de mercado, que son buenas prediciendo el pasado, no el futuro.",
  "pasos_accionables": [
    "Estimar el TAM usando reportes de la industria y benchmarks de competidores",
    "Reducir al SAM considerando limitaciones de canal, idioma o plataforma",
    "Definir el Target Market identificando quién comprará realmente",
    "Realizar una estimación bottom-up basada en datos demográficos o de uso real",
    "Considerar mercados adyacentes y el costo de cambio (switching cost) de clientes actuales",
    "Proyectar el crecimiento a 3-5 años"
  ],
  "entregable_esperado": "Documento con estimación escrita de TAM, SAM y Target Market, y pruebas pass/fail identificadas",
  "nodos_previos": [
    "estrategia_de_innovacion_de_producto",
    "market_size_hypothesis"
  ],
  "nodos_siguientes": [
    "hipotesis_propuesta_de_valor_producto",
    "customer_segments_hypothesis"
  ],
  "condiciones_activacion": [
    "Al validar si una oportunidad de negocio es lo suficientemente grande para justificar la inversión",
    "Antes de comprometer recursos significativos en el desarrollo del producto"
  ]
}