{
  "node_id": "mercados_multilaterales",
  "fase_proyecto": "validacion",
  "titulo_concepto": "Mercados Multilaterales (Multi-Sided Markets)",
  "fuente": "The Startup Owner's Manual - Steve Blank",
  "resumen_teorico": "Mercados donde existen múltiples actores con roles distintos (usuario, comprador, pagador, prescriptor) que deben ser validados por separado. Un ejemplo clásico es un dispositivo médico donde el médico recomienda, el hospital compra, el cirujano implanta y la aseguradora paga. Ignorar alguno de estos lados puede ser un error fatal en la estrategia de canal.",
  "pasos_accionables": [
    "Identifica todos los actores involucrados en la decisión y transacción de compra",
    "Determina quién usa, quién decide, quién compra y quién paga por el producto",
    "Valida la hipótesis de canal para cada lado del mercado por separado",
    "Diseña estrategias de venta diferenciadas para cada tipo de actor"
  ],
  "entregable_esperado": "Un diagrama de canal multilateral con todos los actores y sus roles identificados",
  "nodos_previos": [
    "mapa_de_canal_de_ventas"
  ],
  "nodos_siguientes": [
    "hoja_de_ruta_de_ventas"
  ],
  "condiciones_activacion": [
    "Si el producto involucra múltiples decisores (ej: dispositivos médicos, plataformas B2B2C)"
  ]
}