{
  "node_id": "optimizacion_grow_customers",
  "fase_proyecto": "ejecucion",
  "dominio": "core",
  "titulo_concepto": "Optimización de 'Grow' Customers (Crecer Ingresos por Cliente)",
  "fuente": "The Startup Owner's Manual - Steve Blank",
  "resumen_teorico": "Existen dos formas de hacer crecer a un cliente: lograr que compre más (upsell) o que refiera a otros. Se deben monitorear métricas clave como dólares incrementales por cliente, take rate de upsells, tamaño promedio de orden, y tasa de opt-out, siempre balanceando con la satisfacción del cliente.",
  "pasos_accionables": [
    "Medir dólares incrementales vendidos en promedio a clientes recurrentes (meta: 15%+)",
    "Calcular el 'take rate' de ofertas de upsell y testear ofertas más generosas o urgentes",
    "Aumentar el tamaño promedio de orden mediante suscripciones más largas o bonos",
    "Monitorear tasa de opt-out; si crece 25% o más, suavizar el enfoque de venta",
    "Realizar encuestas de satisfacción y llamadas de agradecimiento que incluyan ofertas sutiles",
    "Diseñar e implementar programas de referidos para atraer nuevos clientes vía clientes existentes"
  ],
  "entregable_esperado": "Plan de crecimiento de ingresos por cliente con métricas de upsell, referidos y satisfacción monitoreadas",
  "nodos_previos": [
    "optimizacion_keep_retencion",
    "ab_testing_optimizacion",
    "funnel_get_customers_optimizacion"
  ],
  "nodos_siguientes": [
    "embudo_get_keep_grow",
    "no_sacrificar_calidad_por_velocidad"
  ],
  "condiciones_activacion": [
    "Cuando el startup ya tiene una base estable de clientes y busca aumentar el valor de vida (LTV)",
    "Cuando se necesita generar crecimiento sin depender exclusivamente de nueva adquisición"
  ],
  "etiqueta_arbol": "Monitorea Upsell y Referencias"
}
