{
  "node_id": "orden_negociacion_puntos",
  "fase_proyecto": "ejecucion",
  "dominio": "core",
  "titulo_concepto": "Estrategia de Orden en la Negociación de Puntos",
  "fuente": "Venture Deals",
  "resumen_teorico": "La secuencia en que se abordan los puntos de un term sheet afecta el resultado de la negociación. Para negociadores menos experimentados se recomienda empezar con puntos fáciles de acordar para generar momentum positivo, dejar la valuación para el final (ya que requiere más rondas de discusión), y evitar negociar punto por punto sin ver el panorama completo cuando la otra parte controla el proceso.",
  "pasos_accionables": [
    "Mapear todos los puntos del term sheet antes de la reunión",
    "Comenzar con acuerdos rápidos y de bajo conflicto (ej. stock option pool)",
    "Dejar la valuación como el último tema a resolver",
    "Si la contraparte fuerza un enfoque punto por punto, evitar comprometerse hasta ver la propuesta completa",
    "Escuchar más de lo que se habla, especialmente al inicio"
  ],
  "entregable_esperado": "Plan de negociación con secuencia de temas definida",
  "nodos_previos": [
    "tecnica_anclaje_negociacion"
  ],
  "nodos_siguientes": [
    "seleccion_abogado_venture",
    "contrarrestar_argumento_mercado"
  ],
  "condiciones_activacion": [
    "Cuando el emprendedor lidera o participa activamente en la negociación de un term sheet"
  ]
}