{
  "node_id": "programa_catorce_pasos_crosby",
  "fase_proyecto": "ejecucion",
  "dominio": "quality",
  "titulo_concepto": "Los Catorce Pasos de Mejora de Calidad de Crosby",
  "fuente": "Quality is free _ the art of making quality certain -- Philip B_ Crosby",
  "resumen_teorico": "Crosby propone un programa estructurado de catorce pasos secuenciales para instalar la mejora de calidad en una organización, desde el compromiso gerencial hasta la repetición continua del ciclo. Cada paso construye sobre el anterior como partes de un todo interrelacionado (como las partes de un gato relacionadas con el gato completo), no como técnicas aisladas sino como un concepto integral que requiere comprensión diaria y no una simple lista de casillas a marcar.",
  "pasos_accionables": [
    "Establecer el compromiso de la gerencia (management commitment)",
    "Formar equipos de mejora de calidad (quality improvement teams)",
    "Medir la calidad actual (quality measurement)",
    "Calcular el costo de la calidad (cost of quality)",
    "Crear conciencia de calidad entre empleados (quality awareness)",
    "Implementar acción correctiva (corrective action)",
    "Planificar el día de Cero Defectos (Zero Defects planning)",
    "Entrenar a supervisores (supervisor training)",
    "Realizar el día de Cero Defectos (ZD day)",
    "Establecer metas (goal setting)",
    "Implementar eliminación de causas de error (Error-Cause Removal)",
    "Reconocer los logros (recognition)",
    "Establecer consejos de calidad (quality councils)",
    "Repetir el ciclo completo (do it over again)"
  ],
  "entregable_esperado": "Un programa formal de catorce pasos documentado e implementado en la organización, con equipos, métricas y consejos de calidad activos.",
  "nodos_previos": [
    "conformance_to_requirements",
    "zero_defects_concepto",
    "consejo_de_calidad_3",
    "costo_de_calidad_crosby"
  ],
  "nodos_siguientes": [
    "consejos_de_calidad",
    "eliminacion_causas_error",
    "make_certain_programa"
  ],
  "condiciones_activacion": [
    "Cuando la organización decide implementar formalmente un programa de mejora de calidad de largo plazo",
    "Cuando se busca un marco estructurado y probado para instalar cultura de calidad"
  ],
  "etiqueta_arbol": "Aplica los Catorce Pasos"
}
