{
  "node_id": "reconocimiento",
  "fase_proyecto": "ejecucion",
  "dominio": "quality",
  "titulo_concepto": "Reconocimiento (Paso 12)",
  "fuente": "Quality is free _ the art of making quality certain -- Philip B_ Crosby",
  "resumen_teorico": "Se establecen programas de premios para reconocer a quienes cumplen sus metas o realizan actos sobresalientes. Es importante no asignar valores relativos a los problemas identificados en la eliminación de causas de error, y los premios no deben ser financieros: lo importante es el reconocimiento genuino.",
  "pasos_accionables": [
    "Diseñar un programa de reconocimiento no financiero",
    "Tratar todos los problemas reportados de manera equitativa",
    "Reconocer públicamente logros de calidad y cumplimiento de metas"
  ],
  "entregable_esperado": "Programa de reconocimiento de calidad implementado y comunicado.",
  "nodos_previos": [
    "eliminacion_causas_error"
  ],
  "nodos_siguientes": [
    "consejo_de_calidad_3"
  ],
  "condiciones_activacion": [
    "Cuando se busca sostener la motivación del equipo tras alcanzar metas de calidad"
  ]
}
