{
  "node_id": "responsabilidad_extendida_productor_2",
  "fase_proyecto": "planificacion",
  "dominio": "environmental",
  "titulo_concepto": "Responsabilidad extendida del productor y stewardship de producto",
  "fuente": "The Green to Gold Business Play - Daniel C. Esty",
  "resumen_teorico": "Los fabricantes son cada vez más responsables por los impactos ambientales de sus productos en todo su ciclo de vida (extended producer responsibility). Regulaciones como WEEE en Europa y EWRA en California obligan a las empresas a gestionar el retorno y disposición de sus productos. El principio 'waste equals food' de McDonough y Braungart (Cradle to Cradle) plantea que el desperdicio de un proceso debe ser insumo de otro, inspirado en los ciclos naturales, distinguiendo entre ciclos técnicos y biológicos.",
  "pasos_accionables": [
    "Diseñar el producto pensando en su disposición final desde el inicio",
    "Evaluar el cumplimiento con regulaciones de responsabilidad extendida (WEEE, EWRA, etc.)",
    "Identificar cómo el desperdicio de producción puede ser insumo de otro proceso",
    "Diferenciar entre ciclos técnicos y biológicos del producto (Cradle to Cradle)"
  ],
  "entregable_esperado": "Plan de gestión de fin de vida del producto y análisis de cumplimiento regulatorio de responsabilidad extendida",
  "nodos_previos": [
    "separar_opciones_dfe"
  ],
  "nodos_siguientes": [
    "certificacion_cradle_to_cradle"
  ],
  "condiciones_activacion": [
    "Si el producto está sujeto a regulaciones de responsabilidad extendida del productor",
    "Si se busca implementar el principio 'waste equals food' en el diseño"
  ]
}