{
  "node_id": "voice_of_customer_estrategico",
  "fase_proyecto": "ideacion",
  "dominio": "core",
  "titulo_concepto": "Voz del Cliente (VoC) a Nivel Estratégico",
  "fuente": "Winning at New Products - Robert G. Cooper",
  "resumen_teorico": "Consiste en entender profundamente las necesidades, problemas y comportamientos de los clientes y usuarios, 'caminando en sus zapatos', para identificar oportunidades estratégicas de innovación. Va más allá de preguntar qué quieren; busca entender el porqué detrás de sus deseos y observar su comportamiento real (ej. el caso de Aero-Flow observando usuarios aspirar el piso en China).",
  "pasos_accionables": [
    "Observar a los clientes usando productos similares en su contexto real (no solo encuestas)",
    "Preguntar qué problemas enfrentan y qué los mantiene despiertos por la noche",
    "Indagar el 'porqué' detrás de cualquier característica o producto que soliciten",
    "Buscar necesidades futuras y planes de los clientes, no solo las actuales",
    "Documentar los 'ahas' o descubrimientos inesperados durante la observación"
  ],
  "entregable_esperado": "Reporte de insights de clientes con necesidades explícitas e implícitas documentadas, incluyendo hallazgos inesperados ('ahas')",
  "nodos_previos": [
    "analisis_competitivo"
  ],
  "nodos_siguientes": [
    "seleccion_arenas_estrategicas",
    "homework_voc_previo_agile"
  ],
  "condiciones_activacion": [
    "Cuando se necesita input real de clientes antes de definir arenas estratégicas",
    "Cuando el mercado es maduro y se buscan nuevas categorías de producto"
  ],
  "etiqueta_arbol": "Camina en los Zapatos del Cliente"
}
