{
  "node_id": "customs_bonded_warehouses",
  "fase_proyecto": "planificacion",
  "dominio": "exportacion",
  "titulo_concepto": "Uso de Almacenes Aduaneros (Bonded Warehouses)",
  "fuente": "A Basic Guide to Exporting (U.S. Commercial Service, 11th Edition)",
  "resumen_teorico": "Un almacén aduanero es un espacio donde bienes dutiable pueden almacenarse o manipularse sin pagar aranceles hasta su retiro. Permite controlar el flujo de efectivo relacionado con el pago de aranceles y almacenar bienes sujetos a cuota.",
  "pasos_accionables": [
    "Evaluar si el flujo de importación se beneficiaría de diferir el pago de aranceles",
    "Contactar a la oficina de U.S. Customs and Border Protection más cercana",
    "Verificar restricciones de cuota que puedan aplicar a la mercancía",
    "Formalizar el bono requerido para operar bajo el almacén aduanero"
  ],
  "entregable_esperado": "Acuerdo o bono formalizado con un almacén aduanero para diferir pagos de aranceles",
  "nodos_previos": [
    "foreign_trade_zones"
  ],
  "nodos_siguientes": [
    "proteccion_propiedad_intelectual_internacional"
  ],
  "condiciones_activacion": [
    "Si la empresa importa mercancía dutiable y busca flexibilidad en el pago de aranceles antes de reexportar o vender localmente"
  ]
}
