{
  "node_id": "construccion_equipo_franquicia",
  "fase_proyecto": "ejecucion",
  "dominio": "franquicias",
  "titulo_concepto": "Construcción del Equipo para el Lanzamiento de la Franquicia",
  "fuente": "Franchise Your Business - Mark Siebert",
  "resumen_teorico": "La mayoría de los nuevos franquiciantes comienzan con equipos muy reducidos, incluso una sola persona cubriendo múltiples roles. El franquiciar añadirá nuevas responsabilidades: marketing de franquicias, ventas, entrenamiento de franquiciados, supervisión de campo y gestión del fondo publicitario. El momento de contratar personal adicional es crítico y debe anticiparse ligeramente a la necesidad real para permitir tiempo de entrenamiento.",
  "pasos_accionables": [
    "Identificar qué roles nuevos requiere el negocio al franquiciar (marketing, ventas, entrenamiento, supervisión de campo)",
    "Determinar qué tareas puede asumir el equipo actual sin contratación adicional",
    "Definir el momento óptimo para nuevas contrataciones, anticipando el tiempo de entrenamiento necesario",
    "Elaborar un perfil de calificaciones mínimas para cada nueva posición"
  ],
  "entregable_esperado": "Un plan de staffing con roles definidos, momento de contratación y calificaciones mínimas por posición",
  "nodos_previos": [
    "cinco_categorias_costos_franquicia",
    "gestion_tiempo_lanzamiento_franquicia"
  ],
  "nodos_siguientes": [
    "outsourcing_funciones_franquicia",
    "entrenar_franquiciados_validacion"
  ],
  "condiciones_activacion": [
    "Si el usuario está por lanzar su programa de franquicias y necesita definir su equipo"
  ],
  "etiqueta_arbol": "Construye tu Equipo de Franquicia"
}
