{
  "node_id": "programas_compra_franquicia",
  "fase_proyecto": "ejecucion",
  "dominio": "franquicias",
  "titulo_concepto": "Programas de Compra y Proveedores Aprobados",
  "fuente": "Franchise Your Business - Mark Siebert",
  "resumen_teorico": "El franquiciante puede negociar condiciones de compra con proveedores clave en beneficio de la red, generando valor tangible y manteniendo control de calidad. También puede designar proveedores exclusivos, lo cual debe justificarse (recetas propietarias, control de marca) para evitar riesgos de antitrust (arreglos de vinculación bajo la Sherman Antitrust Act).",
  "pasos_accionables": [
    "Realizar un análisis costo-beneficio de negociar compras centralizadas",
    "Decidir cómo se distribuirán rebates entre franquiciante, franquiciados o fondo publicitario",
    "Determinar si se designarán proveedores exclusivos y justificar la razón (calidad, receta propietaria)",
    "Revisar con asesoría legal el riesgo de tying arrangements bajo leyes antitrust",
    "Divulgar relaciones de proveedores en el Item 8 del FDD si aplica"
  ],
  "entregable_esperado": "Acuerdo de compras negociado con proveedores y política de proveedores aprobados documentada legalmente",
  "nodos_previos": [
    "soporte_continuo_franquicia"
  ],
  "nodos_siguientes": [
    "seleccion_consultor_franquicias"
  ],
  "condiciones_activacion": [
    "Cuando la red de franquiciados tiene volumen de compra suficiente para negociar con proveedores"
  ]
}
